{"c":["app/layout","app/recreational/page","webpack"],"r":[],"m":["(app-pages-browser)/./node_modules/next/dist/build/webpack/loaders/next-flight-client-entry-loader.js?modules=%7B%22request%22%3A%22E%3A%5C%5Cwebs%5C%5Cmaritima_boats_website%5C%5Cnextjs_space%5C%5Ccomponents%5C%5CClientLayout.tsx%22%2C%22ids%22%3A%5B%22default%22%5D%7D&modules=%7B%22request%22%3A%22E%3A%5C%5Cwebs%5C%5Cmaritima_boats_website%5C%5Cnextjs_space%5C%5Cnode_modules%5C%5Cnext%5C%5Cfont%5C%5Cgoogle%5C%5Ctarget.css%3F%7B%5C%22path%5C%22%3A%5C%22app%5C%5C%5C%5Clayout.tsx%5C%22%2C%5C%22import%5C%22%3A%5C%22Open_Sans%5C%22%2C%5C%22arguments%5C%22%3A%5B%7B%5C%22subsets%5C%22%3A%5B%5C%22latin%5C%22%5D%2C%5C%22variable%5C%22%3A%5C%22--font-opensans%5C%22%2C%5C%22display%5C%22%3A%5C%22swap%5C%22%7D%5D%2C%5C%22variableName%5C%22%3A%5C%22openSans%5C%22%7D%22%2C%22ids%22%3A%5B%5D%7D&modules=%7B%22request%22%3A%22E%3A%5C%5Cwebs%5C%5Cmaritima_boats_website%5C%5Cnextjs_space%5C%5Cnode_modules%5C%5Cnext%5C%5Cfont%5C%5Cgoogle%5C%5Ctarget.css%3F%7B%5C%22path%5C%22%3A%5C%22app%5C%5C%5C%5Clayout.tsx%5C%22%2C%5C%22import%5C%22%3A%5C%22Tinos%5C%22%2C%5C%22arguments%5C%22%3A%5B%7B%5C%22subsets%5C%22%3A%5B%5C%22latin%5C%22%5D%2C%5C%22weight%5C%22%3A%5B%5C%22400%5C%22%2C%5C%22700%5C%22%5D%2C%5C%22variable%5C%22%3A%5C%22--font-times%5C%22%2C%5C%22display%5C%22%3A%5C%22swap%5C%22%7D%5D%2C%5C%22variableName%5C%22%3A%5C%22times%5C%22%7D%22%2C%22ids%22%3A%5B%5D%7D&modules=%7B%22request%22%3A%22E%3A%5C%5Cwebs%5C%5Cmaritima_boats_website%5C%5Cnextjs_space%5C%5Cnode_modules%5C%5Cnext%5C%5Cfont%5C%5Clocal%5C%5Ctarget.css%3F%7B%5C%22path%5C%22%3A%5C%22app%5C%5C%5C%5Clayout.tsx%5C%22%2C%5C%22import%5C%22%3A%5C%22%5C%22%2C%5C%22arguments%5C%22%3A%5B%7B%5C%22src%5C%22%3A%5C%22..%2Fpublic%2Ffonts%2FBrigend%20Signature.otf%5C%22%2C%5C%22variable%5C%22%3A%5C%22--font-brigend%5C%22%2C%5C%22display%5C%22%3A%5C%22swap%5C%22%7D%5D%2C%5C%22variableName%5C%22%3A%5C%22brigend%5C%22%7D%22%2C%22ids%22%3A%5B%5D%7D&modules=%7B%22request%22%3A%22E%3A%5C%5Cwebs%5C%5Cmaritima_boats_website%5C%5Cnextjs_space%5C%5Cnode_modules%5C%5Cnext%5C%5Cfont%5C%5Clocal%5C%5Ctarget.css%3F%7B%5C%22path%5C%22%3A%5C%22app%5C%5C%5C%5Clayout.tsx%5C%22%2C%5C%22import%5C%22%3A%5C%22%5C%22%2C%5C%22arguments%5C%22%3A%5B%7B%5C%22src%5C%22%3A%5C%22..%2Fpublic%2Ffonts%2Fmetag.ttf%5C%22%2C%5C%22variable%5C%22%3A%5C%22--font-metag%5C%22%2C%5C%22display%5C%22%3A%5C%22swap%5C%22%7D%5D%2C%5C%22variableName%5C%22%3A%5C%22metag%5C%22%7D%22%2C%22ids%22%3A%5B%5D%7D&modules=%7B%22request%22%3A%22E%3A%5C%5Cwebs%5C%5Cmaritima_boats_website%5C%5Cnextjs_space%5C%5Cnode_modules%5C%5Cnext%5C%5Cfont%5C%5Clocal%5C%5Ctarget.css%3F%7B%5C%22path%5C%22%3A%5C%22app%5C%5C%5C%5Clayout.tsx%5C%22%2C%5C%22import%5C%22%3A%5C%22%5C%22%2C%5C%22arguments%5C%22%3A%5B%7B%5C%22src%5C%22%3A%5C%22..%2Fpublic%2Ffonts%2Fmetal-gear.ttf%5C%22%2C%5C%22variable%5C%22%3A%5C%22--font-metal%5C%22%2C%5C%22display%5C%22%3A%5C%22swap%5C%22%7D%5D%2C%5C%22variableName%5C%22%3A%5C%22metal%5C%22%7D%22%2C%22ids%22%3A%5B%5D%7D&modules=%7B%22request%22%3A%22E%3A%5C%5Cwebs%5C%5Cmaritima_boats_website%5C%5Cnextjs_space%5C%5Cnode_modules%5C%5Cnext%5C%5Cfont%5C%5Clocal%5C%5Ctarget.css%3F%7B%5C%22path%5C%22%3A%5C%22app%5C%5C%5C%5Clayout.tsx%5C%22%2C%5C%22import%5C%22%3A%5C%22%5C%22%2C%5C%22arguments%5C%22%3A%5B%7B%5C%22src%5C%22%3A%5C%22..%2Fpublic%2Ffonts%2FMonumentExtended-Black.otf%5C%22%2C%5C%22variable%5C%22%3A%5C%22--font-monument%5C%22%2C%5C%22display%5C%22%3A%5C%22swap%5C%22%7D%5D%2C%5C%22variableName%5C%22%3A%5C%22monument%5C%22%7D%22%2C%22ids%22%3A%5B%5D%7D&modules=%7B%22request%22%3A%22E%3A%5C%5Cwebs%5C%5Cmaritima_boats_website%5C%5Cnextjs_space%5C%5Cnode_modules%5C%5Cnext%5C%5Cfont%5C%5Clocal%5C%5Ctarget.css%3F%7B%5C%22path%5C%22%3A%5C%22app%5C%5C%5C%5Clayout.tsx%5C%22%2C%5C%22import%5C%22%3A%5C%22%5C%22%2C%5C%22arguments%5C%22%3A%5B%7B%5C%22src%5C%22%3A%5C%22..%2Fpublic%2Ffonts%2FMyriadPro-Regular.otf%5C%22%2C%5C%22variable%5C%22%3A%5C%22--font-myriad%5C%22%2C%5C%22display%5C%22%3A%5C%22swap%5C%22%7D%5D%2C%5C%22variableName%5C%22%3A%5C%22myriadPro%5C%22%7D%22%2C%22ids%22%3A%5B%5D%7D&modules=%7B%22request%22%3A%22E%3A%5C%5Cwebs%5C%5Cmaritima_boats_website%5C%5Cnextjs_space%5C%5Capp%5C%5Cglobals.css%22%2C%22ids%22%3A%5B%5D%7D&server=false!","(app-pages-browser)/./node_modules/next/font/local/target.css?{\"path\":\"app\\\\layout.tsx\",\"import\":\"\",\"arguments\":[{\"src\":\"../public/fonts/metal-gear.ttf\",\"variable\":\"--font-metal\",\"display\":\"swap\"}],\"variableName\":\"metal\"}"]}